LICENSE
cpstl/__init__.py
cpstl/algorithm/__init__.py
cpstl/algorithm/count/__init__.py
cpstl/algorithm/count/morris_counter.py
cpstl/algorithm/hash/__init__.py
cpstl/algorithm/hash/rolling_hash.py
cpstl/algorithm/hash/universal_hash.py
cpstl/algorithm/hash/utils.py
cpstl/algorithm/similarity/__init__.py
cpstl/algorithm/similarity/interface.py
cpstl/algorithm/similarity/jaccard_similarity.py
cpstl/algorithm/similarity/min_hash.py
cpstl/algorithm/sketch/__init__.py
cpstl/algorithm/sketch/count_min_sketch.py
cpstl/algorithm/sketch/flajolet_martin.py
cpstl/algorithm/sort/__init__.py
cpstl/algorithm/sort/heap_sort.py
cpstl/algorithm/sort/sort.py
cpstl/datatype/__init__.py
cpstl/datatype/graph/__init__.py
cpstl/datatype/graph/graph.py
cpstl/datatype/graph/graph_adj_list.py
cpstl/datatype/heap/__init__.py
cpstl/datatype/heap/heap.py
cpstl/datatype/heap/max_heap.py
cpstl/datatype/heap/min_heap.py
cpstl/patterns/__init__.py
cpstl/patterns/singleton.py
cpstl-0.0.6.dist-info/LICENSE
cpstl-0.0.6.dist-info/WHEEL
cpstl-0.0.6.dist-info/METADATA
cpstl-0.0.6.dist-info/RECORD
