Metadata-Version: 2.1
Name: cpstl
Version: 0.0.6
Summary: Copy and Paste standard library (CPSTL) is a repository with a collection of data structure and algorithms in many different languages
Home-page: https://vincenzopalazzo.github.io/cpstl
License: GNU GENERAL PUBLIC LICENSE v2
Keywords: copy_past_library,heap,max_heap,min_heap
Author: Vincenzo Palazzo
Author-email: vincenzopalazzodev@gmail.com
Requires-Python: >=3.7,<4.0
Classifier: License :: Other/Proprietary License
Classifier: Programming Language :: Python :: 3
Classifier: Programming Language :: Python :: 3.10
Classifier: Programming Language :: Python :: 3.7
Classifier: Programming Language :: Python :: 3.8
Classifier: Programming Language :: Python :: 3.9
Project-URL: Repository, https://github.com/vincenzopalazzo/cpstl
